[
  {
    "date": 1766559662,
    "date_readable": "2025-12-24 02:01:02",
    "timezone": "",
    "timezone_offset": "-0500",
    "hrv": 7.0,
    "unit": "ms",
    "source": "oura_ring_rmssd",
    "measurement_type": "rMSSD"
  },
  {
    "date": 1766559962,
    "date_readable": "2025-12-24 02:06:02",
    "timezone": "",
    "timezone_offset": "-0500",
    "hrv": 6.0,
    "unit": "ms",
    "source": "oura_ring_rmssd",
    "measurement_type": "rMSSD"
  },
  {
    "date": 1766560262,
    "date_readable": "2025-12-24 02:11:02",
    "timezone": "",
    "timezone_offset": "-0500",
    "hrv": 10.0,
    "unit": "ms",
    "source": "oura_ring_rmssd",
    "measurement_type": "rMSSD"
  },
  {
    "date": 1766560562,
    "date_readable": "2025-12-24 02:16:02",
    "timezone": "",
    "timezone_offset": "-0500",
    "hrv": 9.0,
    "unit": "ms",
    "source": "oura_ring_rmssd",
    "measurement_type": "rMSSD"
  },
  {
    "date": 1766560862,
    "date_readable": "2025-12-24 02:21:02",
    "timezone": "",
    "timezone_offset": "-0500",
    "hrv": 9.0,
    "unit": "ms",
    "source": "oura_ring_rmssd",
    "measurement_type": "rMSSD"
  },
  {
    "date": 1766561162,
    "date_readable": "2025-12-24 02:26:02",
    "timezone": "",
    "timezone_offset": "-0500",
    "hrv": 10.0,
    "unit": "ms",
    "source": "oura_ring_rmssd",
    "measurement_type": "rMSSD"
  },
  {
    "date": 1766561462,
    "date_readable": "2025-12-24 02:31:02",
    "timezone": "",
    "timezone_offset": "-0500",
    "hrv": 10.0,
    "unit": "ms",
    "source": "oura_ring_rmssd",
    "measurement_type": "rMSSD"
  },
  {
    "date": 1766561762,
    "date_readable": "2025-12-24 02:36:02",
    "timezone": "",
    "timezone_offset": "-0500",
    "hrv": 11.0,
    "unit": "ms",
    "source": "oura_ring_rmssd",
    "measurement_type": "rMSSD"
  },
  {
    "date": 1766562062,
    "date_readable": "2025-12-24 02:41:02",
    "timezone": "",
    "timezone_offset": "-0500",
    "hrv": 13.0,
    "unit": "ms",
    "source": "oura_ring_rmssd",
    "measurement_type": "rMSSD"
  },
  {
    "date": 1766562362,
    "date_readable": "2025-12-24 02:46:02",
    "timezone": "",
    "timezone_offset": "-0500",
    "hrv": 11.0,
    "unit": "ms",
    "source": "oura_ring_rmssd",
    "measurement_type": "rMSSD"
  },
  {
    "date": 1766562662,
    "date_readable": "2025-12-24 02:51:02",
    "timezone": "",
    "timezone_offset": "-0500",
    "hrv": 12.0,
    "unit": "ms",
    "source": "oura_ring_rmssd",
    "measurement_type": "rMSSD"
  },
  {
    "date": 1766562962,
    "date_readable": "2025-12-24 02:56:02",
    "timezone": "",
    "timezone_offset": "-0500",
    "hrv": 17.0,
    "unit": "ms",
    "source": "oura_ring_rmssd",
    "measurement_type": "rMSSD"
  },
  {
    "date": 1766564162,
    "date_readable": "2025-12-24 03:16:02",
    "timezone": "",
    "timezone_offset": "-0500",
    "hrv": 8.0,
    "unit": "ms",
    "source": "oura_ring_rmssd",
    "measurement_type": "rMSSD"
  },
  {
    "date": 1766564462,
    "date_readable": "2025-12-24 03:21:02",
    "timezone": "",
    "timezone_offset": "-0500",
    "hrv": 11.0,
    "unit": "ms",
    "source": "oura_ring_rmssd",
    "measurement_type": "rMSSD"
  },
  {
    "date": 1766564762,
    "date_readable": "2025-12-24 03:26:02",
    "timezone": "",
    "timezone_offset": "-0500",
    "hrv": 12.0,
    "unit": "ms",
    "source": "oura_ring_rmssd",
    "measurement_type": "rMSSD"
  },
  {
    "date": 1766565062,
    "date_readable": "2025-12-24 03:31:02",
    "timezone": "",
    "timezone_offset": "-0500",
    "hrv": 14.0,
    "unit": "ms",
    "source": "oura_ring_rmssd",
    "measurement_type": "rMSSD"
  },
  {
    "date": 1766565362,
    "date_readable": "2025-12-24 03:36:02",
    "timezone": "",
    "timezone_offset": "-0500",
    "hrv": 10.0,
    "unit": "ms",
    "source": "oura_ring_rmssd",
    "measurement_type": "rMSSD"
  },
  {
    "date": 1766565662,
    "date_readable": "2025-12-24 03:41:02",
    "timezone": "",
    "timezone_offset": "-0500",
    "hrv": 10.0,
    "unit": "ms",
    "source": "oura_ring_rmssd",
    "measurement_type": "rMSSD"
  },
  {
    "date": 1766565962,
    "date_readable": "2025-12-24 03:46:02",
    "timezone": "",
    "timezone_offset": "-0500",
    "hrv": 9.0,
    "unit": "ms",
    "source": "oura_ring_rmssd",
    "measurement_type": "rMSSD"
  },
  {
    "date": 1766566262,
    "date_readable": "2025-12-24 03:51:02",
    "timezone": "",
    "timezone_offset": "-0500",
    "hrv": 12.0,
    "unit": "ms",
    "source": "oura_ring_rmssd",
    "measurement_type": "rMSSD"
  },
  {
    "date": 1766566562,
    "date_readable": "2025-12-24 03:56:02",
    "timezone": "",
    "timezone_offset": "-0500",
    "hrv": 14.0,
    "unit": "ms",
    "source": "oura_ring_rmssd",
    "measurement_type": "rMSSD"
  },
  {
    "date": 1766566862,
    "date_readable": "2025-12-24 04:01:02",
    "timezone": "",
    "timezone_offset": "-0500",
    "hrv": 15.0,
    "unit": "ms",
    "source": "oura_ring_rmssd",
    "measurement_type": "rMSSD"
  },
  {
    "date": 1766567162,
    "date_readable": "2025-12-24 04:06:02",
    "timezone": "",
    "timezone_offset": "-0500",
    "hrv": 16.0,
    "unit": "ms",
    "source": "oura_ring_rmssd",
    "measurement_type": "rMSSD"
  },
  {
    "date": 1766567462,
    "date_readable": "2025-12-24 04:11:02",
    "timezone": "",
    "timezone_offset": "-0500",
    "hrv": 14.0,
    "unit": "ms",
    "source": "oura_ring_rmssd",
    "measurement_type": "rMSSD"
  },
  {
    "date": 1766567762,
    "date_readable": "2025-12-24 04:16:02",
    "timezone": "",
    "timezone_offset": "-0500",
    "hrv": 16.0,
    "unit": "ms",
    "source": "oura_ring_rmssd",
    "measurement_type": "rMSSD"
  },
  {
    "date": 1766568062,
    "date_readable": "2025-12-24 04:21:02",
    "timezone": "",
    "timezone_offset": "-0500",
    "hrv": 15.0,
    "unit": "ms",
    "source": "oura_ring_rmssd",
    "measurement_type": "rMSSD"
  },
  {
    "date": 1766568362,
    "date_readable": "2025-12-24 04:26:02",
    "timezone": "",
    "timezone_offset": "-0500",
    "hrv": 16.0,
    "unit": "ms",
    "source": "oura_ring_rmssd",
    "measurement_type": "rMSSD"
  },
  {
    "date": 1766568662,
    "date_readable": "2025-12-24 04:31:02",
    "timezone": "",
    "timezone_offset": "-0500",
    "hrv": 18.0,
    "unit": "ms",
    "source": "oura_ring_rmssd",
    "measurement_type": "rMSSD"
  },
  {
    "date": 1766568962,
    "date_readable": "2025-12-24 04:36:02",
    "timezone": "",
    "timezone_offset": "-0500",
    "hrv": 15.0,
    "unit": "ms",
    "source": "oura_ring_rmssd",
    "measurement_type": "rMSSD"
  },
  {
    "date": 1766569262,
    "date_readable": "2025-12-24 04:41:02",
    "timezone": "",
    "timezone_offset": "-0500",
    "hrv": 10.0,
    "unit": "ms",
    "source": "oura_ring_rmssd",
    "measurement_type": "rMSSD"
  },
  {
    "date": 1766569562,
    "date_readable": "2025-12-24 04:46:02",
    "timezone": "",
    "timezone_offset": "-0500",
    "hrv": 9.0,
    "unit": "ms",
    "source": "oura_ring_rmssd",
    "measurement_type": "rMSSD"
  },
  {
    "date": 1766569862,
    "date_readable": "2025-12-24 04:51:02",
    "timezone": "",
    "timezone_offset": "-0500",
    "hrv": 7.0,
    "unit": "ms",
    "source": "oura_ring_rmssd",
    "measurement_type": "rMSSD"
  },
  {
    "date": 1766570162,
    "date_readable": "2025-12-24 04:56:02",
    "timezone": "",
    "timezone_offset": "-0500",
    "hrv": 7.0,
    "unit": "ms",
    "source": "oura_ring_rmssd",
    "measurement_type": "rMSSD"
  },
  {
    "date": 1766570462,
    "date_readable": "2025-12-24 05:01:02",
    "timezone": "",
    "timezone_offset": "-0500",
    "hrv": 7.0,
    "unit": "ms",
    "source": "oura_ring_rmssd",
    "measurement_type": "rMSSD"
  },
  {
    "date": 1766570762,
    "date_readable": "2025-12-24 05:06:02",
    "timezone": "",
    "timezone_offset": "-0500",
    "hrv": 9.0,
    "unit": "ms",
    "source": "oura_ring_rmssd",
    "measurement_type": "rMSSD"
  },
  {
    "date": 1766572862,
    "date_readable": "2025-12-24 05:41:02",
    "timezone": "",
    "timezone_offset": "-0500",
    "hrv": 6.0,
    "unit": "ms",
    "source": "oura_ring_rmssd",
    "measurement_type": "rMSSD"
  },
  {
    "date": 1766573162,
    "date_readable": "2025-12-24 05:46:02",
    "timezone": "",
    "timezone_offset": "-0500",
    "hrv": 7.0,
    "unit": "ms",
    "source": "oura_ring_rmssd",
    "measurement_type": "rMSSD"
  },
  {
    "date": 1766573462,
    "date_readable": "2025-12-24 05:51:02",
    "timezone": "",
    "timezone_offset": "-0500",
    "hrv": 8.0,
    "unit": "ms",
    "source": "oura_ring_rmssd",
    "measurement_type": "rMSSD"
  },
  {
    "date": 1766573762,
    "date_readable": "2025-12-24 05:56:02",
    "timezone": "",
    "timezone_offset": "-0500",
    "hrv": 9.0,
    "unit": "ms",
    "source": "oura_ring_rmssd",
    "measurement_type": "rMSSD"
  },
  {
    "date": 1766574062,
    "date_readable": "2025-12-24 06:01:02",
    "timezone": "",
    "timezone_offset": "-0500",
    "hrv": 7.0,
    "unit": "ms",
    "source": "oura_ring_rmssd",
    "measurement_type": "rMSSD"
  },
  {
    "date": 1766574362,
    "date_readable": "2025-12-24 06:06:02",
    "timezone": "",
    "timezone_offset": "-0500",
    "hrv": 7.0,
    "unit": "ms",
    "source": "oura_ring_rmssd",
    "measurement_type": "rMSSD"
  },
  {
    "date": 1766574662,
    "date_readable": "2025-12-24 06:11:02",
    "timezone": "",
    "timezone_offset": "-0500",
    "hrv": 8.0,
    "unit": "ms",
    "source": "oura_ring_rmssd",
    "measurement_type": "rMSSD"
  },
  {
    "date": 1766574962,
    "date_readable": "2025-12-24 06:16:02",
    "timezone": "",
    "timezone_offset": "-0500",
    "hrv": 8.0,
    "unit": "ms",
    "source": "oura_ring_rmssd",
    "measurement_type": "rMSSD"
  },
  {
    "date": 1766575262,
    "date_readable": "2025-12-24 06:21:02",
    "timezone": "",
    "timezone_offset": "-0500",
    "hrv": 8.0,
    "unit": "ms",
    "source": "oura_ring_rmssd",
    "measurement_type": "rMSSD"
  },
  {
    "date": 1766575562,
    "date_readable": "2025-12-24 06:26:02",
    "timezone": "",
    "timezone_offset": "-0500",
    "hrv": 8.0,
    "unit": "ms",
    "source": "oura_ring_rmssd",
    "measurement_type": "rMSSD"
  },
  {
    "date": 1766575862,
    "date_readable": "2025-12-24 06:31:02",
    "timezone": "",
    "timezone_offset": "-0500",
    "hrv": 10.0,
    "unit": "ms",
    "source": "oura_ring_rmssd",
    "measurement_type": "rMSSD"
  },
  {
    "date": 1766576162,
    "date_readable": "2025-12-24 06:36:02",
    "timezone": "",
    "timezone_offset": "-0500",
    "hrv": 10.0,
    "unit": "ms",
    "source": "oura_ring_rmssd",
    "measurement_type": "rMSSD"
  },
  {
    "date": 1766576462,
    "date_readable": "2025-12-24 06:41:02",
    "timezone": "",
    "timezone_offset": "-0500",
    "hrv": 12.0,
    "unit": "ms",
    "source": "oura_ring_rmssd",
    "measurement_type": "rMSSD"
  },
  {
    "date": 1766576762,
    "date_readable": "2025-12-24 06:46:02",
    "timezone": "",
    "timezone_offset": "-0500",
    "hrv": 11.0,
    "unit": "ms",
    "source": "oura_ring_rmssd",
    "measurement_type": "rMSSD"
  },
  {
    "date": 1766577062,
    "date_readable": "2025-12-24 06:51:02",
    "timezone": "",
    "timezone_offset": "-0500",
    "hrv": 10.0,
    "unit": "ms",
    "source": "oura_ring_rmssd",
    "measurement_type": "rMSSD"
  },
  {
    "date": 1766577362,
    "date_readable": "2025-12-24 06:56:02",
    "timezone": "",
    "timezone_offset": "-0500",
    "hrv": 11.0,
    "unit": "ms",
    "source": "oura_ring_rmssd",
    "measurement_type": "rMSSD"
  },
  {
    "date": 1766586662,
    "date_readable": "2025-12-24 09:31:02",
    "timezone": "",
    "timezone_offset": "-0500",
    "hrv": 15.0,
    "unit": "ms",
    "source": "oura_ring_rmssd",
    "measurement_type": "rMSSD"
  },
  {
    "date": 1766586962,
    "date_readable": "2025-12-24 09:36:02",
    "timezone": "",
    "timezone_offset": "-0500",
    "hrv": 13.0,
    "unit": "ms",
    "source": "oura_ring_rmssd",
    "measurement_type": "rMSSD"
  },
  {
    "date": 1766587262,
    "date_readable": "2025-12-24 09:41:02",
    "timezone": "",
    "timezone_offset": "-0500",
    "hrv": 12.0,
    "unit": "ms",
    "source": "oura_ring_rmssd",
    "measurement_type": "rMSSD"
  },
  {
    "date": 1766587562,
    "date_readable": "2025-12-24 09:46:02",
    "timezone": "",
    "timezone_offset": "-0500",
    "hrv": 14.0,
    "unit": "ms",
    "source": "oura_ring_rmssd",
    "measurement_type": "rMSSD"
  },
  {
    "date": 1766587862,
    "date_readable": "2025-12-24 09:51:02",
    "timezone": "",
    "timezone_offset": "-0500",
    "hrv": 14.0,
    "unit": "ms",
    "source": "oura_ring_rmssd",
    "measurement_type": "rMSSD"
  },
  {
    "date": 1766588162,
    "date_readable": "2025-12-24 09:56:02",
    "timezone": "",
    "timezone_offset": "-0500",
    "hrv": 13.0,
    "unit": "ms",
    "source": "oura_ring_rmssd",
    "measurement_type": "rMSSD"
  },
  {
    "date": 1766588462,
    "date_readable": "2025-12-24 10:01:02",
    "timezone": "",
    "timezone_offset": "-0500",
    "hrv": 15.0,
    "unit": "ms",
    "source": "oura_ring_rmssd",
    "measurement_type": "rMSSD"
  },
  {
    "date": 1766588762,
    "date_readable": "2025-12-24 10:06:02",
    "timezone": "",
    "timezone_offset": "-0500",
    "hrv": 14.0,
    "unit": "ms",
    "source": "oura_ring_rmssd",
    "measurement_type": "rMSSD"
  },
  {
    "date": 1766589062,
    "date_readable": "2025-12-24 10:11:02",
    "timezone": "",
    "timezone_offset": "-0500",
    "hrv": 15.0,
    "unit": "ms",
    "source": "oura_ring_rmssd",
    "measurement_type": "rMSSD"
  },
  {
    "date": 1766589362,
    "date_readable": "2025-12-24 10:16:02",
    "timezone": "",
    "timezone_offset": "-0500",
    "hrv": 13.0,
    "unit": "ms",
    "source": "oura_ring_rmssd",
    "measurement_type": "rMSSD"
  },
  {
    "date": 1766589662,
    "date_readable": "2025-12-24 10:21:02",
    "timezone": "",
    "timezone_offset": "-0500",
    "hrv": 15.0,
    "unit": "ms",
    "source": "oura_ring_rmssd",
    "measurement_type": "rMSSD"
  },
  {
    "date": 1766589962,
    "date_readable": "2025-12-24 10:26:02",
    "timezone": "",
    "timezone_offset": "-0500",
    "hrv": 13.0,
    "unit": "ms",
    "source": "oura_ring_rmssd",
    "measurement_type": "rMSSD"
  },
  {
    "date": 1766590262,
    "date_readable": "2025-12-24 10:31:02",
    "timezone": "",
    "timezone_offset": "-0500",
    "hrv": 16.0,
    "unit": "ms",
    "source": "oura_ring_rmssd",
    "measurement_type": "rMSSD"
  },
  {
    "date": 1766590562,
    "date_readable": "2025-12-24 10:36:02",
    "timezone": "",
    "timezone_offset": "-0500",
    "hrv": 18.0,
    "unit": "ms",
    "source": "oura_ring_rmssd",
    "measurement_type": "rMSSD"
  },
  {
    "date": 1766590862,
    "date_readable": "2025-12-24 10:41:02",
    "timezone": "",
    "timezone_offset": "-0500",
    "hrv": 13.0,
    "unit": "ms",
    "source": "oura_ring_rmssd",
    "measurement_type": "rMSSD"
  },
  {
    "date": 1766591162,
    "date_readable": "2025-12-24 10:46:02",
    "timezone": "",
    "timezone_offset": "-0500",
    "hrv": 16.0,
    "unit": "ms",
    "source": "oura_ring_rmssd",
    "measurement_type": "rMSSD"
  },
  {
    "date": 1766591462,
    "date_readable": "2025-12-24 10:51:02",
    "timezone": "",
    "timezone_offset": "-0500",
    "hrv": 17.0,
    "unit": "ms",
    "source": "oura_ring_rmssd",
    "measurement_type": "rMSSD"
  },
  {
    "date": 1766591762,
    "date_readable": "2025-12-24 10:56:02",
    "timezone": "",
    "timezone_offset": "-0500",
    "hrv": 16.0,
    "unit": "ms",
    "source": "oura_ring_rmssd",
    "measurement_type": "rMSSD"
  },
  {
    "date": 1766592062,
    "date_readable": "2025-12-24 11:01:02",
    "timezone": "",
    "timezone_offset": "-0500",
    "hrv": 8.0,
    "unit": "ms",
    "source": "oura_ring_rmssd",
    "measurement_type": "rMSSD"
  },
  {
    "date": 1766592962,
    "date_readable": "2025-12-24 11:16:02",
    "timezone": "",
    "timezone_offset": "-0500",
    "hrv": 10.0,
    "unit": "ms",
    "source": "oura_ring_rmssd",
    "measurement_type": "rMSSD"
  },
  {
    "date": 1766593262,
    "date_readable": "2025-12-24 11:21:02",
    "timezone": "",
    "timezone_offset": "-0500",
    "hrv": 9.0,
    "unit": "ms",
    "source": "oura_ring_rmssd",
    "measurement_type": "rMSSD"
  },
  {
    "date": 1766593562,
    "date_readable": "2025-12-24 11:26:02",
    "timezone": "",
    "timezone_offset": "-0500",
    "hrv": 9.0,
    "unit": "ms",
    "source": "oura_ring_rmssd",
    "measurement_type": "rMSSD"
  },
  {
    "date": 1766593862,
    "date_readable": "2025-12-24 11:31:02",
    "timezone": "",
    "timezone_offset": "-0500",
    "hrv": 9.0,
    "unit": "ms",
    "source": "oura_ring_rmssd",
    "measurement_type": "rMSSD"
  },
  {
    "date": 1766594162,
    "date_readable": "2025-12-24 11:36:02",
    "timezone": "",
    "timezone_offset": "-0500",
    "hrv": 9.0,
    "unit": "ms",
    "source": "oura_ring_rmssd",
    "measurement_type": "rMSSD"
  },
  {
    "date": 1766594462,
    "date_readable": "2025-12-24 11:41:02",
    "timezone": "",
    "timezone_offset": "-0500",
    "hrv": 8.0,
    "unit": "ms",
    "source": "oura_ring_rmssd",
    "measurement_type": "rMSSD"
  },
  {
    "date": 1766594762,
    "date_readable": "2025-12-24 11:46:02",
    "timezone": "",
    "timezone_offset": "-0500",
    "hrv": 8.0,
    "unit": "ms",
    "source": "oura_ring_rmssd",
    "measurement_type": "rMSSD"
  },
  {
    "date": 1766595062,
    "date_readable": "2025-12-24 11:51:02",
    "timezone": "",
    "timezone_offset": "-0500",
    "hrv": 9.0,
    "unit": "ms",
    "source": "oura_ring_rmssd",
    "measurement_type": "rMSSD"
  },
  {
    "date": 1766595362,
    "date_readable": "2025-12-24 11:56:02",
    "timezone": "",
    "timezone_offset": "-0500",
    "hrv": 8.0,
    "unit": "ms",
    "source": "oura_ring_rmssd",
    "measurement_type": "rMSSD"
  },
  {
    "date": 1766595662,
    "date_readable": "2025-12-24 12:01:02",
    "timezone": "",
    "timezone_offset": "-0500",
    "hrv": 10.0,
    "unit": "ms",
    "source": "oura_ring_rmssd",
    "measurement_type": "rMSSD"
  },
  {
    "date": 1766595962,
    "date_readable": "2025-12-24 12:06:02",
    "timezone": "",
    "timezone_offset": "-0500",
    "hrv": 10.0,
    "unit": "ms",
    "source": "oura_ring_rmssd",
    "measurement_type": "rMSSD"
  },
  {
    "date": 1766596262,
    "date_readable": "2025-12-24 12:11:02",
    "timezone": "",
    "timezone_offset": "-0500",
    "hrv": 9.0,
    "unit": "ms",
    "source": "oura_ring_rmssd",
    "measurement_type": "rMSSD"
  },
  {
    "date": 1766596562,
    "date_readable": "2025-12-24 12:16:02",
    "timezone": "",
    "timezone_offset": "-0500",
    "hrv": 7.0,
    "unit": "ms",
    "source": "oura_ring_rmssd",
    "measurement_type": "rMSSD"
  },
  {
    "date": 1766596862,
    "date_readable": "2025-12-24 12:21:02",
    "timezone": "",
    "timezone_offset": "-0500",
    "hrv": 6.0,
    "unit": "ms",
    "source": "oura_ring_rmssd",
    "measurement_type": "rMSSD"
  },
  {
    "date": 1766597162,
    "date_readable": "2025-12-24 12:26:02",
    "timezone": "",
    "timezone_offset": "-0500",
    "hrv": 8.0,
    "unit": "ms",
    "source": "oura_ring_rmssd",
    "measurement_type": "rMSSD"
  },
  {
    "date": 1766597462,
    "date_readable": "2025-12-24 12:31:02",
    "timezone": "",
    "timezone_offset": "-0500",
    "hrv": 13.0,
    "unit": "ms",
    "source": "oura_ring_rmssd",
    "measurement_type": "rMSSD"
  }
]